CHANGES.rst
LICENSE
MANIFEST.in
Makefile
README.rst
setup.py
aiocouchdb/__init__.py
aiocouchdb/authn.py
aiocouchdb/client.py
aiocouchdb/errors.py
aiocouchdb/feeds.py
aiocouchdb/hdrs.py
aiocouchdb/multipart.py
aiocouchdb/version.py
aiocouchdb/views.py
aiocouchdb.egg-info/PKG-INFO
aiocouchdb.egg-info/SOURCES.txt
aiocouchdb.egg-info/dependency_links.txt
aiocouchdb.egg-info/not-zip-safe
aiocouchdb.egg-info/requires.txt
aiocouchdb.egg-info/top_level.txt
aiocouchdb/tests/__init__.py
aiocouchdb/tests/test_authn.py
aiocouchdb/tests/test_client.py
aiocouchdb/tests/test_errors.py
aiocouchdb/tests/test_feeds.py
aiocouchdb/tests/utils.py
aiocouchdb/v1/__init__.py
aiocouchdb/v1/attachment.py
aiocouchdb/v1/authdb.py
aiocouchdb/v1/config.py
aiocouchdb/v1/database.py
aiocouchdb/v1/designdoc.py
aiocouchdb/v1/document.py
aiocouchdb/v1/security.py
aiocouchdb/v1/server.py
aiocouchdb/v1/session.py
aiocouchdb/v1/tests/__init__.py
aiocouchdb/v1/tests/test_attachment.py
aiocouchdb/v1/tests/test_authdb.py
aiocouchdb/v1/tests/test_config.py
aiocouchdb/v1/tests/test_database.py
aiocouchdb/v1/tests/test_designdoc.py
aiocouchdb/v1/tests/test_document.py
aiocouchdb/v1/tests/test_security.py
aiocouchdb/v1/tests/test_server.py
aiocouchdb/v1/tests/test_session.py
aiocouchdb/v1/tests/utils.py
docs/Makefile
docs/common.rst
docs/conf.py
docs/index.rst
docs/make.bat
docs/v1/index.rst