Metadata-Version: 1.1
Name: aiocouchdb
Version: 0.9.1
Summary: CouchDB client built on top of aiohttp (asyncio)
Home-page: https://github.com/kxepal/aiocouchdb
Author: Alexander Shorin
Author-email: kxepal@gmail.com
License: BSD
Platform: UNKNOWN
Classifier: Development Status :: 4 - Beta
Classifier: Intended Audience :: Developers
Classifier: License :: OSI Approved :: BSD License
Classifier: Operating System :: OS Independent
Classifier: Programming Language :: Python
Classifier: Programming Language :: Python :: 3
Classifier: Programming Language :: Python :: 3.3
Classifier: Programming Language :: Python :: 3.4
Classifier: Topic :: Database :: Front-Ends
Classifier: Topic :: Software Development :: Libraries :: Python Modules
